LICENSE
MANIFEST.in
README.md
setup.py
/home/eeojun/code/monocypher-py/src/monocypher-3.1.2-src/monocypher.c
/home/eeojun/code/monocypher-py/src/monocypher-3.1.2-src/optional/monocypher-ed25519.c
src/build.py
src/monocypher_exposed.h
src/monocypher/__init__.py
src/monocypher/hash.py
src/monocypher/public.py
src/monocypher/pwhash.py
src/monocypher/secret.py
src/monocypher/signing.py
src/monocypher/utils.py
src/monocypher-3.1.2-src/monocypher.c
src/monocypher-3.1.2-src/monocypher.h
src/monocypher-3.1.2-src/optional/monocypher-ed25519.c
src/monocypher-3.1.2-src/optional/monocypher-ed25519.h
src/monocypher/bindings/__init__.py
src/monocypher/bindings/crypto_aead.py
src/monocypher/bindings/crypto_ed25519.py
src/monocypher/bindings/crypto_hash.py
src/monocypher/bindings/crypto_hidden.py
src/monocypher/bindings/crypto_public.py
src/monocypher/bindings/crypto_pwhash.py
src/monocypher/bindings/crypto_sign.py
src/monocypher/bindings/crypto_utils.py
src/monocypher_py.egg-info/PKG-INFO
src/monocypher_py.egg-info/SOURCES.txt
src/monocypher_py.egg-info/dependency_links.txt
src/monocypher_py.egg-info/not-zip-safe
src/monocypher_py.egg-info/requires.txt
src/monocypher_py.egg-info/top_level.txt