Metadata-Version: 2.1
Name: monocypher-py
Version: 0.0.3
Summary: Python binding to the Monocypher library
Home-page: https://github.com/eugene-eeo/monocypher-py
Author: Eeo Jun
Author-email: 141bytes@gmail.com
License: CC0 1.0 Universal
Platform: UNKNOWN
Requires-Python: >=3.6
Provides-Extra: tests
Provides-Extra: docs
License-File: LICENSE
